talking_equipment_sdk/__init__.py
talking_equipment_sdk/config.py
talking_equipment_sdk/shortcuts.py
talking_equipment_sdk/utils.py
talking_equipment_sdk/api/__init__.py
talking_equipment_sdk/api/handlers.py
talking_equipment_sdk/api/requests.py
talking_equipment_sdk/api/responses.py
talking_equipment_sdk/api/utils.py
talking_equipment_sdk/api/data_source/__init__.py
talking_equipment_sdk/api/data_source/choices.py
talking_equipment_sdk/api/data_source/handlers.py
talking_equipment_sdk/data/__init__.py
talking_equipment_sdk/data/choices.py
talking_equipment_sdk/data/data.py
talking_equipment_sdk/data/enums.py
talking_equipment_sdk/data/mixins.py
talking_equipment_sdk/data/utils.py
talking_equipment_sdk/data/control/__init__.py
talking_equipment_sdk/data/control/data.py
talking_equipment_sdk/data/control/tests.py
talking_equipment_sdk/data/counter/__init__.py
talking_equipment_sdk/data/counter/data.py
talking_equipment_sdk/data/counter/tests.py
talking_equipment_sdk/data/current/__init__.py
talking_equipment_sdk/data/current/data.py
talking_equipment_sdk/data/current/tests.py
talking_equipment_sdk/data/frequency/__init__.py
talking_equipment_sdk/data/frequency/data.py
talking_equipment_sdk/data/frequency/tests.py
talking_equipment_sdk/data/power_factor/__init__.py
talking_equipment_sdk/data/power_factor/data.py
talking_equipment_sdk/data/power_factor/tests.py
talking_equipment_sdk/data/power_meter/__init__.py
talking_equipment_sdk/data/power_meter/data.py
talking_equipment_sdk/data/power_meter/tests/__init__.py
talking_equipment_sdk/data/power_meter/tests/test_power_meter.py
talking_equipment_sdk/data/power_meter/tests/test_single_phase_power_meter.py
talking_equipment_sdk/data/power_meter/tests/test_three_phase_power_meter.py
talking_equipment_sdk/data/temperature/__init__.py
talking_equipment_sdk/data/temperature/data.py
talking_equipment_sdk/data/temperature/tests.py
talking_equipment_sdk/data/tests/__init__.py
talking_equipment_sdk-0.1.2.dist-info/LICENSE.md
talking_equipment_sdk-0.1.2.dist-info/METADATA
talking_equipment_sdk-0.1.2.dist-info/WHEEL
talking_equipment_sdk-0.1.2.dist-info/top_level.txt
talking_equipment_sdk-0.1.2.dist-info/RECORD
